{"game":"ck3","name":"CK3 Kino","mods":[{"displayName":"Asia Expansion Project","enabled":true,"position":0,"steamId":"2970440958"},{"displayName":"Community Flavor Pack","enabled":true,"position":1,"steamId":"2220098919"},{"displayName":"AEP-CFP Compatibility Patch","enabled":true,"position":2,"steamId":"2972335233"},{"displayName":"Impregnate Spouse","enabled":true,"position":3,"steamId":"2216917595"},{"displayName":"Artifact Manager","enabled":true,"position":4,"steamId":"2886417277"},{"displayName":"Auto conversion","enabled":true,"position":5,"steamId":"2694172949"},{"displayName":"Auto increase control","enabled":true,"position":6,"steamId":"2729685999"},{"displayName":"Auto promote culture","enabled":true,"position":7,"steamId":"2689410555"},{"displayName":"Border Disputes","enabled":true,"position":8,"steamId":"2702831494"},{"displayName":"Great Empire Wars","enabled":true,"position":9,"steamId":"2688782754"},{"displayName":"Houses Traditions","enabled":true,"position":10,"steamId":"2590650832"},{"displayName":"Mass Demand Conversion","enabled":true,"position":11,"steamId":"2753176859"},{"displayName":"More Traditions v2","enabled":true,"position":12,"steamId":"2893793966"},{"displayName":"Prisoners of War","enabled":true,"position":13,"steamId":"2511247871"},{"displayName":"Quando Sumus - Decisions of CK3","enabled":true,"position":14,"steamId":"2818339011"},{"displayName":"VIET Events - A Flavor and Immersion Event Mod","enabled":true,"position":15,"steamId":"2227658180"}]}
